hold_your_shell/hold_your_shell.py
hold_your_shell-0.1.6.dist-info/licenses/LICENSE.txt
hold_your_shell-0.1.6.dist-info/METADATA
hold_your_shell-0.1.6.dist-info/WHEEL
hold_your_shell-0.1.6.dist-info/entry_points.txt
hold_your_shell-0.1.6.dist-info/top_level.txt
hold_your_shell-0.1.6.dist-info/RECORD
