Metadata-Version: 2.4
Name: hold-your-shell
Version: 0.1.6
Summary: Preview and confirm scripts before executing them.
Project-URL: Homepage, https://github.com/EnigmaCurry/hold-your-shell
Project-URL: Repository, https://github.com/EnigmaCurry/hold-your-shell
Requires-Python: >=3.7
License-File: LICENSE.txt
Dynamic: license-file
